{"nodes": [{"id": "19"}, {"id": "2"}, {"id": "12"}, {"id": "18"}, {"id": "20"}, {"id": "15"}, {"id": "14"}, {"id": "7"}, {"id": "4"}, {"id": "5"}, {"id": "8"}, {"id": "6"}, {"id": "13"}, {"id": "11"}, {"id": "3"}, {"id": "10"}, {"id": "17"}, {"id": "16"}, {"id": "9"}, {"id": "1"}, {"id": "21"}], "links": [["19", "2", "12", "18"], ["19", "20"], ["15", "14"], ["4", "5"], ["7", "8", "6"], ["19", "13"], ["11", "3", "10"], ["19", "16"], ["5", "6", "10", "9"], ["2", "1"], ["12", "11", "3"], ["20", "15", "13", "16", "21"], ["18", "17"], ["8", "6", "9"]]}